nr_vocabularies/__init__.py
nr_vocabularies/config.py
nr_vocabularies/customfields.py
nr_vocabularies/ext.py
nr_vocabularies/translations.py
nr_vocabularies/fixtures/__init__.py
nr_vocabularies/fixtures/access-rights.yaml
nr_vocabularies/fixtures/catalogue.yaml
nr_vocabularies/fixtures/community-types.yaml
nr_vocabularies/fixtures/contributor-types.yaml
nr_vocabularies/fixtures/convert_to_yaml.py
nr_vocabularies/fixtures/countries.yaml
nr_vocabularies/fixtures/degree-grantors.yaml
nr_vocabularies/fixtures/documentation_cs.md
nr_vocabularies/fixtures/funders.yaml
nr_vocabularies/fixtures/institutions.yaml
nr_vocabularies/fixtures/item-relation-types.yaml
nr_vocabularies/fixtures/languages.yaml
nr_vocabularies/fixtures/resource-types.yaml
nr_vocabularies/fixtures/rights.yaml
nr_vocabularies/fixtures/subject-categories.yaml
nr_vocabularies/translations/messages.pot
nr_vocabularies/translations/cs/LC_MESSAGES/messages.mo
nr_vocabularies/translations/cs/LC_MESSAGES/messages.po
nr_vocabularies/translations/en/LC_MESSAGES/messages.mo
nr_vocabularies/translations/en/LC_MESSAGES/messages.po
nr_vocabularies-2.1.20.dist-info/METADATA
nr_vocabularies-2.1.20.dist-info/WHEEL
nr_vocabularies-2.1.20.dist-info/entry_points.txt
nr_vocabularies-2.1.20.dist-info/top_level.txt
nr_vocabularies-2.1.20.dist-info/RECORD
