Metadata-Version: 2.4
Name: nr-vocabularies
Version: 2.1.20
Summary: A sample application for nr_vocabularies
Requires-Dist: oarepo-vocabularies>=1.0.0
Provides-Extra: tests
Requires-Dist: oarepo-vocabularies[tests]>=1.0.0; extra == "tests"
Provides-Extra: oarepo-11
Requires-Dist: oarepo<12,>=11; extra == "oarepo-11"
Provides-Extra: oarepo-12
Requires-Dist: oarepo<13,>=12; extra == "oarepo-12"
Provides-Extra: devs
Requires-Dist: black; extra == "devs"
Requires-Dist: isort; extra == "devs"
Requires-Dist: autoflake; extra == "devs"
